Metadata-Version: 2.4
Name: random-allocation-fork
Version: 0.2.12
Summary: Tools for analyzing and comparing different sampling schemes in differential privacy
Author-email: Moshe Shenfeld <mosheshenfeld@gmail.com>
License: MIT
Project-URL: Homepage, https://github.com/moshenfeld/random_allocation
Project-URL: Bug Tracker, https://github.com/moshenfeld/random_allocation/issues
Keywords: differential-privacy,random-allocation,privacy-analysis
Classifier: Development Status :: 3 - Alpha
Classifier: Intended Audience :: Science/Research
Classifier: License :: OSI Approved :: MIT License
Classifier: Programming Language :: Python :: 3
Classifier: Programming Language :: Python :: 3.8
Classifier: Programming Language :: Python :: 3.9
Classifier: Programming Language :: Python :: 3.10
Classifier: Topic :: Scientific/Engineering :: Mathematics
Requires-Python: >=3.8
License-File: LICENSE
Requires-Dist: dp_accounting>=0.4.4
Requires-Dist: scipy>=1.7.0
Requires-Dist: matplotlib>=3.4.0
Requires-Dist: numba>=0.60.0
Requires-Dist: numpy<3.0,>=2.0.2
Provides-Extra: dev
Requires-Dist: pytest>=6.0; extra == "dev"
Requires-Dist: black>=21.0; extra == "dev"
Requires-Dist: flake8>=3.9; extra == "dev"
Dynamic: license-file
